[
  {
  "type": "24 Hours of Le Mans",
  "participants": " Toyota Porsche G-Drive Rebellion Racing ",
  "winner": "Toyota",
  "day":"Tuesday",
  "age1":"children",
  "age2":"young",
  "age3":"old",
  "count1": 1111,
  "count2":6666,
  "count3": 3333
},
  {
    "type": "Rally",
    "participants": "Peugeot Honda Suzuki Audi",
    "winner": "Honda",
    "day": "Friday",
    "age1": "children",
    "age2": "young",
    "age3": "old",
    "count1": 800,
    "count2": 6200,
    "count3": 300
  }
]